{
    "equipments": [
        {
            "id": "iron_sword",
            "name": "铁剑",
            "slot": "Weapon",
            "bonusAttack": 10,
            "bonusDefense": 0,
            "bonusHp": 0,
            "bonusQi": 0,
            "bonusSpeed": 0
        },
        {
            "id": "leather_armor",
            "name": "皮甲",
            "slot": "Armor",
            "bonusAttack": 0,
            "bonusDefense": 3,
            "bonusHp": 0,
            "bonusQi": 0,
            "bonusSpeed": 0
        },
        {
            "id": "silver_armor",
            "name": "银鳞甲",
            "slot": "Armor",
            "bonusAttack": 0,
            "bonusDefense": 15,
            "bonusHp": 50,
            "bonusQi": 0,
            "bonusSpeed": 0
        },
        {
            "id": "swift_boots",
            "name": "疾风靴",
            "slot": "Shoes",
            "bonusAttack": 0,
            "bonusDefense": 0,
            "bonusHp": 0,
            "bonusQi": 0,
            "bonusSpeed": 10
        },
        {
            "id": "speed_boots",
            "name": "疾风靴",
            "slot": "Shoes",
            "bonusAttack": 0,
            "bonusDefense": 0,
            "bonusHp": 0,
            "bonusQi": 0,
            "bonusSpeed": 3
        }
    ]
}
